smtp_email_notifier_utils/__init__.py
smtp_email_notifier_utils/console_helper.py
smtp_email_notifier_utils/constants.py
smtp_email_notifier_utils/file_utils.py
smtp_email_notifier_utils/notifier.py
smtp_email_notifier_utils/send_notification_email.py
smtp_email_notifier_utils/system_caller.py
smtp_email_notifier_utils-0.2.0.dist-info/AUTHORS.rst
smtp_email_notifier_utils-0.2.0.dist-info/METADATA
smtp_email_notifier_utils-0.2.0.dist-info/WHEEL
smtp_email_notifier_utils-0.2.0.dist-info/entry_points.txt
smtp_email_notifier_utils-0.2.0.dist-info/top_level.txt
smtp_email_notifier_utils-0.2.0.dist-info/RECORD
