Metadata-Version: 2.2
Name: smtp_email_notifier_utils
Version: 0.2.0
Summary: A simple module for send SMTP-based notification emails.
Author-email: Jaideep Sundaram <jai.python3@gmail.com>
Project-URL: Homepage, https://github.com/jai-python3/smtp-email-notifier-utils
Keywords: smtp_email_notifier_utils
Classifier: Development Status :: 2 - Pre-Alpha
Classifier: Intended Audience :: Developers
Classifier: Natural Language :: English
Classifier: Programming Language :: Python :: 3.12
Requires-Python: >=3.10
License-File: AUTHORS.rst
Requires-Dist: Click>=7.0
Requires-Dist: PyYAML
Requires-Dist: Rich
Requires-Dist: singleton-decorator
Requires-Dist: python-dotenv
Provides-Extra: dev
Requires-Dist: pytest>=6.2; extra == "dev"
Requires-Dist: pytest-mock>=3.6; extra == "dev"
Requires-Dist: coverage>=5.5; extra == "dev"
